[{"__type__":"cc.SpriteFrame","content":{"name":"Avatar26","texture":"391TnV8P5FkIfgXYR5DcAW","rect":[1419,2,150,124],"offset":[-1,-4],"originalSize":[174,132],"capInsets":[0,0,0,0]}},{"__type__":"cc.SpriteFrame","content":{"name":"Avatar34","texture":"391TnV8P5FkIfgXYR5DcAW","rect":[483,2,154,128],"offset":[-5,-1],"originalSize":[174,132],"capInsets":[0,0,0,0]}},{"__type__":"cc.SpriteFrame","content":{"name":"Avatar39","texture":"391TnV8P5FkIfgXYR5DcAW","rect":[952,2,156,122],"offset":[-5,-5],"originalSize":[174,132],"capInsets":[0,0,0,0]}},{"__type__":"cc.SpriteFrame","content":{"name":"Avatar20","texture":"391TnV8P5FkIfgXYR5DcAW","rect":[640,2,152,128],"offset":[-3,-2],"originalSize":[174,132],"capInsets":[0,0,0,0]}},{"__type__":"cc.SpriteFrame","content":{"name":"chamxanh","texture":"391TnV8P5FkIfgXYR5DcAW","rect":[1848,227,34,34],"offset":[0,0],"originalSize":[34,34],"capInsets":[0,0,0,0]}},{"__type__":"cc.SpriteFrame","content":{"name":"Avatar37","texture":"391TnV8P5FkIfgXYR5DcAW","rect":[1066,262,122,130],"offset":[6,0],"originalSize":[174,132],"rotated":1,"capInsets":[0,0,0,0]}},{"__type__":"cc.SpriteFrame","content":{"name":"AnDanh","texture":"391TnV8P5FkIfgXYR5DcAW","rect":[2,2,160,130],"offset":[2,-1],"originalSize":[174,132],"capInsets":[0,0,0,0]}},{"__type__":"cc.SpriteFrame","content":{"name":"Avatar35","texture":"391TnV8P5FkIfgXYR5DcAW","rect":[1334,266,112,132],"offset":[4,0],"originalSize":[174,132],"rotated":1,"capInsets":[0,0,0,0]}},{"__type__":"cc.SpriteFrame","content":{"name":"Avatar36","texture":"391TnV8P5FkIfgXYR5DcAW","rect":[1487,264,122,122],"offset":[-1,-1],"originalSize":[174,132],"capInsets":[0,0,0,0]}},{"__type__":"cc.SpriteFrame","content":{"name":"Avatar33","texture":"391TnV8P5FkIfgXYR5DcAW","rect":[2,135,156,130],"offset":[-1,-1],"originalSize":[174,132],"capInsets":[0,0,0,0]}},{"__type__":"cc.SpriteFrame","content":{"name":"Avatar15","texture":"391TnV8P5FkIfgXYR5DcAW","rect":[1711,264,108,128],"offset":[4,-2],"originalSize":[174,132],"rotated":1,"capInsets":[0,0,0,0]}},{"__type__":"cc.SpriteFrame","content":{"name":"Avatar11","texture":"391TnV8P5FkIfgXYR5DcAW","rect":[580,262,124,128],"offset":[-3,-2],"originalSize":[174,132],"rotated":1,"capInsets":[0,0,0,0]}},{"__type__":"cc.SpriteFrame","content":{"name":"Avatar24","texture":"391TnV8P5FkIfgXYR5DcAW","rect":[314,133,144,126],"offset":[-2,-3],"originalSize":[174,132],"capInsets":[0,0,0,0]}},{"__type__":"cc.SpriteFrame","content":{"name":"Avatar30","texture":"391TnV8P5FkIfgXYR5DcAW","rect":[1102,127,136,132],"offset":[-4,0],"originalSize":[174,132],"capInsets":[0,0,0,0]}},{"__type__":"cc.SpriteFrame","content":{"name":"Avatar38","texture":"391TnV8P5FkIfgXYR5DcAW","rect":[165,131,146,132],"offset":[-1,0],"originalSize":[174,132],"capInsets":[0,0,0,0]}},{"__type__":"cc.SpriteFrame","content":{"name":"Avatar16","texture":"391TnV8P5FkIfgXYR5DcAW","rect":[1376,131,108,132],"offset":[0,0],"originalSize":[174,132],"capInsets":[0,0,0,0]}},{"__type__":"cc.SpriteFrame","content":{"name":"Avatar29","texture":"391TnV8P5FkIfgXYR5DcAW","rect":[1572,2,146,124],"offset":[1,-4],"originalSize":[174,132],"capInsets":[0,0,0,0]}},{"__type__":"cc.SpriteFrame","content":{"name":"Avatar31","texture":"391TnV8P5FkIfgXYR5DcAW","rect":[314,262,130,124],"offset":[-5,-4],"originalSize":[174,132],"capInsets":[0,0,0,0]}},{"__type__":"cc.SpriteFrame","content":{"name":"Avatar28","texture":"391TnV8P5FkIfgXYR5DcAW","rect":[795,2,154,124],"offset":[-2,-4],"originalSize":[174,132],"capInsets":[0,0,0,0]}},{"__type__":"cc.SpriteFrame","content":{"name":"Avatar7","texture":"391TnV8P5FkIfgXYR5DcAW","rect":[2,268,130,118],"offset":[-1,-7],"originalSize":[174,132],"capInsets":[0,0,0,0]}},{"__type__":"cc.SpriteFrame","content":{"name":"Avatar14","texture":"391TnV8P5FkIfgXYR5DcAW","rect":[461,133,126,130],"offset":[6,0],"originalSize":[174,132],"rotated":1,"capInsets":[0,0,0,0]}},{"__type__":"cc.SpriteFrame","content":{"name":"Avatar10","texture":"391TnV8P5FkIfgXYR5DcAW","rect":[1620,129,90,128],"offset":[2,-2],"originalSize":[174,132],"capInsets":[0,0,0,0]}},{"__type__":"cc.SpriteFrame","content":{"name":"Avatar8","texture":"391TnV8P5FkIfgXYR5DcAW","rect":[161,266,140,120],"offset":[3,-6],"originalSize":[174,132],"capInsets":[0,0,0,0]}},{"__type__":"cc.SpriteFrame","content":{"name":"Avatar19","texture":"391TnV8P5FkIfgXYR5DcAW","rect":[1199,266,114,132],"offset":[0,0],"originalSize":[174,132],"rotated":1,"capInsets":[0,0,0,0]}},{"__type__":"cc.SpriteFrame","content":{"name":"Avatar25","texture":"391TnV8P5FkIfgXYR5DcAW","rect":[1620,260,88,126],"offset":[2,-3],"originalSize":[174,132],"capInsets":[0,0,0,0]}},{"__type__":"cc.SpriteFrame","content":{"name":"Avatar0","texture":"391TnV8P5FkIfgXYR5DcAW","rect":[1241,131,132,132],"offset":[4,0],"originalSize":[174,132],"capInsets":[0,0,0,0]}},{"__type__":"cc.SpriteFrame","content":{"name":"Avatar12","texture":"391TnV8P5FkIfgXYR5DcAW","rect":[1266,2,150,126],"offset":[-2,-2],"originalSize":[174,132],"capInsets":[0,0,0,0]}},{"__type__":"cc.SpriteFrame","content":{"name":"Avatar23","texture":"391TnV8P5FkIfgXYR5DcAW","rect":[447,262,124,130],"offset":[-2,-1],"originalSize":[174,132],"rotated":1,"capInsets":[0,0,0,0]}},{"__type__":"cc.SpriteFrame","content":{"name":"Avatar18","texture":"391TnV8P5FkIfgXYR5DcAW","rect":[951,262,112,124],"offset":[-5,-4],"originalSize":[174,132],"capInsets":[0,0,0,0]}},{"__type__":"cc.SpriteFrame","content":{"name":"Avatar5","texture":"391TnV8P5FkIfgXYR5DcAW","rect":[594,133,120,126],"offset":[0,-3],"originalSize":[174,132],"capInsets":[0,0,0,0]}},{"__type__":"cc.SpriteFrame","content":{"name":"Avatar21","texture":"391TnV8P5FkIfgXYR5DcAW","rect":[1713,133,128,132],"offset":[-4,0],"originalSize":[174,132],"rotated":1,"capInsets":[0,0,0,0]}},{"__type__":"cc.SpriteAtlas","_name":"Rik_Avatar.plist","_spriteFrames":{"AnDanh":{"__uuid__":"203JSqCBZFO4J7Q9FRq3yG"},"Avatar0":{"__uuid__":"7f6uYbhdRJjJGJrlCEkCfb"},"Avatar1":{"__uuid__":"a3Kx1LFbBH2ZJGLXe1ismG"},"Avatar10":{"__uuid__":"62r2vvO/9AwqFCSK1SCz3W"},"Avatar11":{"__uuid__":"366kcsD8ZKGZNm/vz5MyUw"},"Avatar12":{"__uuid__":"83I9gVSTRNyJmyyxSQDIOg"},"Avatar13":{"__uuid__":"ed+f/NIT9PVrVgCkP2HshL"},"Avatar14":{"__uuid__":"5cE3i4ZmlDvqC3+pUxqCWJ"},"Avatar15":{"__uuid__":"35eBFs5BZDD4EGEdu3AKb5"},"Avatar16":{"__uuid__":"4eNcEpVCxIMbWduV8BFP2s"},"Avatar17":{"__uuid__":"e6k6i01ndFho5A2Czrs+xN"},"Avatar18":{"__uuid__":"8cnsbRCGdHf5wRBx/o4ePr"},"Avatar19":{"__uuid__":"75dxjUyW1GT6MJ8nv+4Xb3"},"Avatar2":{"__uuid__":"a6rD8bOKROHo2++RhNDfja"},"Avatar20":{"__uuid__":"0fFv+KBflIo7TjdGOXP4ro"},"Avatar21":{"__uuid__":"93y59NL6JDe7ZzRBGgpNz1"},"Avatar22":{"__uuid__":"c99OcqMrtPqI3gYB5CjYuu"},"Avatar23":{"__uuid__":"86OlMIwtdBfad+RlK58c5e"},"Avatar24":{"__uuid__":"39pyUp9otL7aB2nW+v2A7+"},"Avatar25":{"__uuid__":"78f7WVqXdHr72X2jUNIAOd"},"Avatar26":{"__uuid__":"009YsNSh5ERIhX8gLBZZ1v"},"Avatar27":{"__uuid__":"e1BeL7yY1D4boqhiu6DyG+"},"Avatar28":{"__uuid__":"5aT0DpUVVOLoPmfTmUFKAa"},"Avatar29":{"__uuid__":"58X7gk3o9FQJ+/TAbKS3jl"},"Avatar3":{"__uuid__":"fd0OKD+SFLjrG6u9YWArMW"},"Avatar30":{"__uuid__":"3bZPssC7JAZ4EbyGezXYUy"},"Avatar31":{"__uuid__":"59VmGaCrVKOoOPLyk0gMd3"},"Avatar32":{"__uuid__":"a1ElvRiZRNE63Zq6/0MiPU"},"Avatar33":{"__uuid__":"33lkAVHvxDI4Z0KXTbNzdm"},"Avatar34":{"__uuid__":"02d7FJG4hLdZ51paqyyTB9"},"Avatar35":{"__uuid__":"28KUnZrAlA0LTifrEuMFBt"},"Avatar36":{"__uuid__":"31hxwjRlxAJKsOtFDbQjqA"},"Avatar37":{"__uuid__":"1b0Hx/VAtMX6Dg6Rf1PONI"},"Avatar38":{"__uuid__":"3chDvDSOtEF7i+rCBuEjjO"},"Avatar39":{"__uuid__":"0eSK2aIFlDebi1qBMP/qJE"},"Avatar4":{"__uuid__":"b7sy1xg1RNfaQ6Mf6Fs/Yy"},"Avatar5":{"__uuid__":"8fkUVqvJVFzryHpraBsk3C"},"Avatar6":{"__uuid__":"e3Qnn56vRForj0sXczcz8D"},"Avatar7":{"__uuid__":"5aXQlEJwhI9rJVb3cCJx0S"},"Avatar8":{"__uuid__":"72fQHVwFpPUYezIsVL+hKe"},"Avatar9":{"__uuid__":"ceXPlMgV1DoI3y5fP9fkBd"},"bgAvatarCard":{"__uuid__":"dab0u11B5J4pAavVCzg61g"},"chamxanh":{"__uuid__":"12p4YVR/NG1q8MZxHI3ELS"},"vectorSmartObject@3x":{"__uuid__":"e7HhHTchFBibOFOvRIKcQ/"}}},{"__type__":"cc.SpriteFrame","content":{"name":"Avatar32","texture":"391TnV8P5FkIfgXYR5DcAW","rect":[1721,2,146,128],"offset":[-1,-2],"originalSize":[174,132],"capInsets":[0,0,0,0]}},{"__type__":"cc.SpriteFrame","content":{"name":"Avatar1","texture":"391TnV8P5FkIfgXYR5DcAW","rect":[963,127,136,132],"offset":[-2,0],"originalSize":[174,132],"capInsets":[0,0,0,0]}},{"__type__":"cc.SpriteFrame","content":{"name":"Avatar2","texture":"391TnV8P5FkIfgXYR5DcAW","rect":[1487,129,130,132],"offset":[-6,0],"originalSize":[174,132],"capInsets":[0,0,0,0]}},{"__type__":"cc.SpriteFrame","content":{"name":"Avatar4","texture":"391TnV8P5FkIfgXYR5DcAW","rect":[711,262,120,124],"offset":[3,-3],"originalSize":[174,132],"capInsets":[0,0,0,0]}},{"__type__":"cc.SpriteFrame","content":{"name":"Avatar22","texture":"391TnV8P5FkIfgXYR5DcAW","rect":[834,262,114,124],"offset":[-8,-4],"originalSize":[174,132],"capInsets":[0,0,0,0]}},{"__type__":"cc.SpriteFrame","content":{"name":"Avatar9","texture":"391TnV8P5FkIfgXYR5DcAW","rect":[1111,2,152,122],"offset":[-2,-5],"originalSize":[174,132],"capInsets":[0,0,0,0]}},{"__type__":"cc.SpriteFrame","content":{"name":"bgAvatarCard","texture":"391TnV8P5FkIfgXYR5DcAW","rect":[1870,2,174,49],"offset":[0,0],"originalSize":[174,49],"rotated":1,"capInsets":[0,0,0,0]}},{"__type__":"cc.SpriteFrame","content":{"name":"Avatar27","texture":"391TnV8P5FkIfgXYR5DcAW","rect":[326,2,154,128],"offset":[-4,-2],"originalSize":[174,132],"capInsets":[0,0,0,0]}},{"__type__":"cc.SpriteFrame","content":{"name":"Avatar6","texture":"391TnV8P5FkIfgXYR5DcAW","rect":[952,2,156,122],"offset":[-5,-5],"originalSize":[174,132],"capInsets":[0,0,0,0]}},{"__type__":"cc.SpriteFrame","content":{"name":"Avatar17","texture":"391TnV8P5FkIfgXYR5DcAW","rect":[832,129,130,128],"offset":[7,-2],"originalSize":[174,132],"rotated":1,"capInsets":[0,0,0,0]}},{"__type__":"cc.SpriteFrame","content":{"name":"vectorSmartObject@3x","texture":"391TnV8P5FkIfgXYR5DcAW","rect":[1848,179,56,45],"offset":[0,0],"originalSize":[56,45],"capInsets":[0,0,0,0]}},{"__type__":"cc.SpriteFrame","content":{"name":"Avatar13","texture":"391TnV8P5FkIfgXYR5DcAW","rect":[165,2,158,126],"offset":[-8,-3],"originalSize":[174,132],"capInsets":[0,0,0,0]}},{"__type__":"cc.SpriteFrame","content":{"name":"Avatar3","texture":"391TnV8P5FkIfgXYR5DcAW","rect":[717,133,112,126],"offset":[-2,-3],"originalSize":[174,132],"capInsets":[0,0,0,0]}}]